<?xml version="1.0" encoding="utf-8" ?>
<Data>
	<Header>
		<req_id>1234</req_id>
		<req_app>IBS</req_app>
		<srv>CBS037</srv>
		<srv_app>CBS</srv_app>
		<req_time>2012-10-22 11:56:15.1234</req_time>
	</Header>
	<Body>
		<createCA>
			<channel>SMSBK01</channel>
			<hostDate>020712</hostDate>
			<hostId>TT110001</hostId>
			<branchCode>020</branchCode>
			<currencyType>VND</currencyType>
			<cifNumber>212868</cifNumber>
			<accountNumber>02001010666741</accountNumber>
			<accountType>CAM1</accountType>
			<accountName>LE ANH TUAN</accountName>
			<modeOfOperation>1</modeOfOperation>
		</createCA>
	</Body>
</Data>

